nonebot_plugin_number_detection/__init__.py
nonebot_plugin_number_detection/config.py
nonebot_plugin_number_detection-0.1.2.dist-info/METADATA
nonebot_plugin_number_detection-0.1.2.dist-info/WHEEL
nonebot_plugin_number_detection-0.1.2.dist-info/top_level.txt
nonebot_plugin_number_detection-0.1.2.dist-info/RECORD
