Metadata-Version: 2.1
Name: nonebot-plugin-number-detection
Version: 0.1.2
Summary: Default template for PDM package
Author-email: zhongwen-4 <2401128923@qq.com>
License: MIT
Requires-Python: >=3.9.0
Requires-Dist: nonebot2>=2.4.1
Requires-Dist: nonebot-adapter-onebot>=2.4.6
